odoo/addons/hr_timesheet_time_restriction/README.rst
odoo/addons/hr_timesheet_time_restriction/__init__.py
odoo/addons/hr_timesheet_time_restriction/__manifest__.py
odoo/addons/hr_timesheet_time_restriction/i18n/hr_timesheet_time_restriction.pot
odoo/addons/hr_timesheet_time_restriction/i18n/it.po
odoo/addons/hr_timesheet_time_restriction/models/__init__.py
odoo/addons/hr_timesheet_time_restriction/models/account_analytic_line.py
odoo/addons/hr_timesheet_time_restriction/models/project_project.py
odoo/addons/hr_timesheet_time_restriction/models/res_config_settings.py
odoo/addons/hr_timesheet_time_restriction/readme/CONFIGURE.rst
odoo/addons/hr_timesheet_time_restriction/readme/CONTRIBUTORS.rst
odoo/addons/hr_timesheet_time_restriction/readme/CREDITS.rst
odoo/addons/hr_timesheet_time_restriction/readme/DESCRIPTION.rst
odoo/addons/hr_timesheet_time_restriction/security/res_groups.xml
odoo/addons/hr_timesheet_time_restriction/static/description/icon.png
odoo/addons/hr_timesheet_time_restriction/static/description/index.html
odoo/addons/hr_timesheet_time_restriction/tests/__init__.py
odoo/addons/hr_timesheet_time_restriction/tests/test_disabled_hr_timesheet_time_restriction.py
odoo/addons/hr_timesheet_time_restriction/tests/test_enabled_hr_timesheet_time_restriction.py
odoo/addons/hr_timesheet_time_restriction/views/project_project_view.xml
odoo/addons/hr_timesheet_time_restriction/views/res_config_settings_view.xml
odoo14_addon_hr_timesheet_time_restriction-14.0.1.0.1.dist-info/METADATA
odoo14_addon_hr_timesheet_time_restriction-14.0.1.0.1.dist-info/WHEEL
odoo14_addon_hr_timesheet_time_restriction-14.0.1.0.1.dist-info/top_level.txt
odoo14_addon_hr_timesheet_time_restriction-14.0.1.0.1.dist-info/RECORD
